iLiaShah/PostData.py
iLiaShah/WebAdress.py
iLiaShah/__init__.py
iLiaShah/method.py
iLiaShah/sendserver.py
iLiaShah/Configs/__init__.py
iLiaShah-3.8.1.dist-info/LICENCE
iLiaShah-3.8.1.dist-info/METADATA
iLiaShah-3.8.1.dist-info/WHEEL
iLiaShah-3.8.1.dist-info/top_level.txt
iLiaShah-3.8.1.dist-info/RECORD
